moveread/pipelines/ocr_predict/__init__.py
moveread/pipelines/ocr_predict/__init__.pyi
moveread/pipelines/ocr_predict/main.py
moveread/pipelines/ocr_predict/spec.py
moveread_pipelines_ocr_predict-0.2.6.dist-info/METADATA
moveread_pipelines_ocr_predict-0.2.6.dist-info/WHEEL
moveread_pipelines_ocr_predict-0.2.6.dist-info/top_level.txt
moveread_pipelines_ocr_predict-0.2.6.dist-info/RECORD
