Metadata-Version: 2.1
Name: moveread-pipelines-ocr-predict
Version: 0.2.6
Summary: OCR Prediction pipeline for Moveread
Author-email: Marcel Claramunt <marcel@moveread.com>
Project-URL: repo, https://github.com/moveread/dfy-pipeline.git
Requires-Python: >=3.10
Requires-Dist: lazy-loader
Requires-Dist: tf-serving
Requires-Dist: pipeteer
Requires-Dist: python-kv
Requires-Dist: haskellian
